LICENSE
README.md
ipc.py
setup.cfg
setup.py
ipc.egg-info/PKG-INFO
ipc.egg-info/SOURCES.txt
ipc.egg-info/dependency_links.txt
ipc.egg-info/not-zip-safe
ipc.egg-info/top_level.txt